gpyt/__init__.py
gpyt/__main__.py
gpyt/app.py
gpyt/args.py
gpyt/assistant.py
gpyt/components/assistant_app.py
gpyt/components/assistant_response.py
gpyt/components/assistant_responses.py
gpyt/components/conversation_option.py
gpyt/components/options.py
gpyt/components/past_conversations.py
gpyt/components/user_input.py
gpyt/components/vim_list.py
gpyt/config.py
gpyt/conversation.py
gpyt/exception.py
gpyt/free_assistant.py
gpyt/id.py
gpyt/palm_assistant.py
gpyt/styles.cssx
gpyt-0.2.23.dist-info/METADATA
gpyt-0.2.23.dist-info/WHEEL
gpyt-0.2.23.dist-info/entry_points.txt
gpyt-0.2.23.dist-info/RECORD
