Metadata-Version: 2.1
Name: gpyt
Version: 0.2.23
Summary: GPT on the command line.
Author: Justin Stitt
Author-email: jstitt007@gmail.com
Requires-Python: >=3.11,<4.0
Classifier: Programming Language :: Python :: 3
Classifier: Programming Language :: Python :: 3.11
Requires-Dist: google-generativeai (>=0.1.0rc3,<0.2.0)
Requires-Dist: gpt4free (>=1.0.2,<2.0.0)
Requires-Dist: openai (>=0.27.5,<0.28.0)
Requires-Dist: openai-async (>=0.0.3,<0.0.4)
Requires-Dist: pydantic (>=1.10.7,<2.0.0)
Requires-Dist: pyperclip (>=1.8.2,<2.0.0)
Requires-Dist: python-dotenv (>=1.0.0,<2.0.0)
Requires-Dist: textual[dev] (>=0.29.0,<0.30.0)
Requires-Dist: tiktoken (>=0.4.0,<0.5.0)
